black_swan_ai/__init__.py
black_swan_ai/_base_client.py
black_swan_ai/_client.py
black_swan_ai/_compat.py
black_swan_ai/_constants.py
black_swan_ai/_exceptions.py
black_swan_ai/_files.py
black_swan_ai/_models.py
black_swan_ai/_qs.py
black_swan_ai/_resource.py
black_swan_ai/_response.py
black_swan_ai/_streaming.py
black_swan_ai/_types.py
black_swan_ai/_version.py
black_swan_ai/py.typed
black_swan_ai/_utils/__init__.py
black_swan_ai/_utils/_logs.py
black_swan_ai/_utils/_proxy.py
black_swan_ai/_utils/_reflection.py
black_swan_ai/_utils/_streams.py
black_swan_ai/_utils/_sync.py
black_swan_ai/_utils/_transform.py
black_swan_ai/_utils/_typing.py
black_swan_ai/_utils/_utils.py
black_swan_ai/lib/.keep
black_swan_ai/resources/__init__.py
black_swan_ai/resources/moderation.py
black_swan_ai/resources/chat/__init__.py
black_swan_ai/resources/chat/chat.py
black_swan_ai/resources/chat/completion.py
black_swan_ai/types/__init__.py
black_swan_ai/types/create_moderation_response.py
black_swan_ai/types/moderation_create_params.py
black_swan_ai/types/chat/__init__.py
black_swan_ai/types/chat/chat_completion_choice.py
black_swan_ai/types/chat/chat_completion_delta.py
black_swan_ai/types/chat/chat_completion_delta_tool_call.py
black_swan_ai/types/chat/chat_completion_delta_tool_call_function.py
black_swan_ai/types/chat/chat_completion_message.py
black_swan_ai/types/chat/chat_completion_stream_choice.py
black_swan_ai/types/chat/chat_completion_tool_call.py
black_swan_ai/types/chat/chat_completion_tool_call_function.py
black_swan_ai/types/chat/completion_create_params.py
black_swan_ai/types/chat/completion_create_response.py
black_swan_ai/types/chat/create_chat_completion_response.py
black_swan_ai/types/chat/create_chat_completion_stream_response.py
blackswan_api-0.1.0a43.dist-info/METADATA
blackswan_api-0.1.0a43.dist-info/WHEEL
blackswan_api-0.1.0a43.dist-info/licenses/LICENSE
blackswan_api-0.1.0a43.dist-info/RECORD
